repositories/__init__.py
repositories/repositories.py
polly_repositories-0.0.3.dist-info/METADATA
polly_repositories-0.0.3.dist-info/WHEEL
polly_repositories-0.0.3.dist-info/top_level.txt
polly_repositories-0.0.3.dist-info/RECORD
