Metadata-Version: 2.1
Name: polly-repositories
Version: 0.0.3
Summary: Interact with Polly Repositories
Home-page: UNKNOWN
Author: Bisweswar Martha
Author-email: bisweswar.martha@elucidata.io
License: UNKNOWN
Platform: UNKNOWN
